lvnlp/__init__.py
lvnlp/ner_allennlp.py
lvnlp/nlppipe_client.py
lvnlp-0.0.2.dist-info/METADATA
lvnlp-0.0.2.dist-info/WHEEL
lvnlp-0.0.2.dist-info/top_level.txt
lvnlp-0.0.2.dist-info/RECORD
