Metadata-Version: 2.1
Name: lvnlp
Version: 0.0.2
Summary: Latvian NLP Tools
Home-page: https://gitlab.com/ailab/lvnlp
License: gpl-3.0
Keywords: nlp,lv
Platform: UNKNOWN
Requires-Dist: allennlp (==0.9.0)
Requires-Dist: flask (==1.1.1)
Requires-Dist: requests (==2.22.0)
